id_schema/__init__.py
id_schema/id_schema.py
id_schema/components/__init__.py
id_schema/components/base_component.py
id_schema/components/exact_literal.py
id_schema/components/one_of.py
id_schema/components/random_group.py
id_schema-1.0.9.dist-info/LICENSE
id_schema-1.0.9.dist-info/METADATA
id_schema-1.0.9.dist-info/WHEEL
id_schema-1.0.9.dist-info/top_level.txt
id_schema-1.0.9.dist-info/RECORD
