Metadata-Version: 2.1
Name: id-schema
Version: 1.0.9
Summary: ID Schema
Home-page: https://github.com/tibotix/id_schema
Author: Tibotix
Author-email: tizian@seehaus.net
Requires-Python: >=3.8, <4
License-File: LICENSE
Provides-Extra: test
Requires-Dist: pytest ; extra == 'test'
Requires-Dist: pytest-benchmark ; extra == 'test'
